hwpapi/FilePathCheckerModuleExample.dll
hwpapi/__init__.py
hwpapi/_modidx.py
hwpapi/actions.py
hwpapi/classes.py
hwpapi/constants.py
hwpapi/core.py
hwpapi/dataclasses.py
hwpapi/functions.py
hwpapi/logging.py
hwpapi/parametersets.py
hwpapi/_pyinstaller/__init__.py
hwpapi/_pyinstaller/hook-hwpapi.py
hwpapi-0.0.2.5.dist-info/licenses/LICENSE
nbs/__init__.py
nbs/action_info.py
~bs/__init__.py
~wpapi/__init__.py
~wpapi/_modidx.py
~wpapi/actions.py
~wpapi/core.py
~wpapi/functions.py
~wpapi/methods.py
hwpapi-0.0.2.5.dist-info/METADATA
hwpapi-0.0.2.5.dist-info/WHEEL
hwpapi-0.0.2.5.dist-info/entry_points.txt
hwpapi-0.0.2.5.dist-info/top_level.txt
hwpapi-0.0.2.5.dist-info/RECORD
